confdsl/__init__.py
confdsl/hcl.py
confdsl/json.py
confdsl-0.1.0.dist-info/WHEEL
confdsl-0.1.0.dist-info/METADATA
confdsl-0.1.0.dist-info/RECORD
