Metadata-Version: 2.1
Name: confdsl
Version: 0.1.0
Summary: wrapper to make reading config from various DSLs easy
License: MIT
Author: Ayush
Author-email: ayushshanker@outlook.in
Requires-Python: >=3.8,<4.0
Classifier: License :: OSI Approved :: MIT License
Classifier: Programming Language :: Python :: 3
Classifier: Programming Language :: Python :: 3.8
Requires-Dist: pyhcl (>=0.4.4,<0.5.0)
